daml/__init__.py
daml/_internal/detectors/__init__.py
daml/_internal/detectors/clusterer.py
daml/_internal/detectors/drift/__init__.py
daml/_internal/detectors/drift/base.py
daml/_internal/detectors/drift/cvm.py
daml/_internal/detectors/drift/ks.py
daml/_internal/detectors/drift/mmd.py
daml/_internal/detectors/drift/torch.py
daml/_internal/detectors/drift/uncertainty.py
daml/_internal/detectors/duplicates.py
daml/_internal/detectors/linter.py
daml/_internal/detectors/ood/__init__.py
daml/_internal/detectors/ood/ae.py
daml/_internal/detectors/ood/aegmm.py
daml/_internal/detectors/ood/base.py
daml/_internal/detectors/ood/llr.py
daml/_internal/detectors/ood/vae.py
daml/_internal/detectors/ood/vaegmm.py
daml/_internal/flags.py
daml/_internal/metrics/__init__.py
daml/_internal/metrics/base.py
daml/_internal/metrics/ber.py
daml/_internal/metrics/coverage.py
daml/_internal/metrics/divergence.py
daml/_internal/metrics/hash.py
daml/_internal/metrics/parity.py
daml/_internal/metrics/stats.py
daml/_internal/metrics/uap.py
daml/_internal/metrics/utils.py
daml/_internal/models/__init__.py
daml/_internal/models/pytorch/__init__.py
daml/_internal/models/pytorch/autoencoder.py
daml/_internal/models/pytorch/blocks.py
daml/_internal/models/pytorch/utils.py
daml/_internal/models/tensorflow/__init__.py
daml/_internal/models/tensorflow/autoencoder.py
daml/_internal/models/tensorflow/gmm.py
daml/_internal/models/tensorflow/losses.py
daml/_internal/models/tensorflow/pixelcnn.py
daml/_internal/models/tensorflow/trainer.py
daml/_internal/models/tensorflow/utils.py
daml/_internal/workflows/sufficiency.py
daml/detectors/__init__.py
daml/flags/__init__.py
daml/metrics/__init__.py
daml/models/__init__.py
daml/models/tensorflow/__init__.py
daml/models/torch/__init__.py
daml/py.typed
daml/workflows/__init__.py
daml-0.56.0.dist-info/LICENSE.txt
daml-0.56.0.dist-info/METADATA
daml-0.56.0.dist-info/WHEEL
daml-0.56.0.dist-info/RECORD
