Metadata-Version: 2.1
Name: daml
Version: 0.56.0
Summary: DAML provides a simple interface to characterize image data and its impact on model performance across classification and object-detection tasks
Home-page: https://daml.ai/
License: MIT
Author: Andrew Weng
Author-email: andrew.weng@ariacoustics.com
Maintainer: ARiA
Maintainer-email: daml@ariacoustics.com
Requires-Python: >=3.9,<3.12
Classifier: Development Status :: 4 - Beta
Classifier: Intended Audience :: Science/Research
Classifier: License :: OSI Approved :: MIT License
Classifier: Operating System :: OS Independent
Classifier: Programming Language :: Python :: 3
Classifier: Programming Language :: Python :: 3.9
Classifier: Programming Language :: Python :: 3.10
Classifier: Programming Language :: Python :: 3.11
Classifier: Programming Language :: Python :: 3 :: Only
Classifier: Topic :: Scientific/Engineering
Provides-Extra: all
Provides-Extra: maite
Provides-Extra: tensorflow
Provides-Extra: torch
Requires-Dist: hdbscan (>=0.8.36)
Requires-Dist: maite ; extra == "maite" or extra == "all"
Requires-Dist: matplotlib ; extra == "torch" or extra == "all"
Requires-Dist: numpy (>1.24.3)
Requires-Dist: nvidia-cudnn-cu11 (>=8.6.0.163) ; extra == "tensorflow" or extra == "torch" or extra == "all"
Requires-Dist: pillow (>=10.3.0)
Requires-Dist: scikit-learn (>=1.2.1)
Requires-Dist: scipy (>=1.10)
Requires-Dist: tensorflow (>=2.14.1) ; extra == "tensorflow" or extra == "all"
Requires-Dist: tensorflow-io-gcs-filesystem (>=0.35.0) ; extra == "tensorflow" or extra == "all"
Requires-Dist: tensorflow_probability (>=0.22.1) ; extra == "tensorflow" or extra == "all"
Requires-Dist: torch (>=2.0.1,!=2.2.0) ; extra == "torch" or extra == "all"
Requires-Dist: xxhash (>=3.3)
Project-URL: Documentation, https://daml.readthedocs.io/
Project-URL: Repository, https://github.com/aria-ml/daml/
